[{"timestamp":1592312326802,"files":[{"filename":"ssr-bundle.42b42.css","previous":1389,"size":0,"diff":-1389},{"filename":"ssr-bundle.js","previous":4170,"size":0,"diff":-4170},{"filename":"sw-esm.js","previous":0,"size":741,"diff":741},{"filename":"sw.js","previous":0,"size":738,"diff":738},{"filename":"bundle.76aa4.css","previous":0,"size":546,"diff":546},{"filename":"bundle.72487.esm.js","previous":0,"size":8158,"diff":8158},{"filename":"polyfills.989dd.esm.js","previous":0,"size":2012,"diff":2012},{"filename":"route-Privacy/index.tsx.chunk.19aa0.css","previous":0,"size":278,"diff":278},{"filename":"route-Privacy/index.tsx.chunk.85f50.esm.js","previous":0,"size":433,"diff":433},{"filename":"route-home/index.tsx.chunk.f4379.css","previous":0,"size":786,"diff":786},{"filename":"route-home/index.tsx.chunk.d3be5.esm.js","previous":0,"size":917,"diff":917},{"filename":"route-notfound/index.tsx.chunk.8dc19.css","previous":0,"size":73,"diff":73},{"filename":"route-notfound/index.tsx.chunk.b11b8.esm.js","previous":0,"size":340,"diff":340},{"filename":"bundle.bcfa9.js","previous":0,"size":8143,"diff":8143},{"filename":"polyfills.84c13.js","previous":0,"size":2012,"diff":2012},{"filename":"route-Privacy/index.tsx.chunk.56bc9.js","previous":0,"size":439,"diff":439},{"filename":"route-home/index.tsx.chunk.7876f.js","previous":0,"size":923,"diff":923},{"filename":"route-notfound/index.tsx.chunk.dc1d3.js","previous":0,"size":340,"diff":340}]},{"timestamp":1592312321061,"files":[{"filename":"sw-esm.js","previous":741,"size":0,"diff":-741},{"filename":"sw.js","previous":738,"size":0,"diff":-738},{"filename":"bundle.76aa4.css","previous":546,"size":0,"diff":-546},{"filename":"bundle.72487.esm.js","previous":8158,"size":0,"diff":-8158},{"filename":"polyfills.989dd.esm.js","previous":2012,"size":0,"diff":-2012},{"filename":"route-Privacy/index.tsx.chunk.19aa0.css","previous":278,"size":0,"diff":-278},{"filename":"route-Privacy/index.tsx.chunk.85f50.esm.js","previous":433,"size":0,"diff":-433},{"filename":"route-home/index.tsx.chunk.f4379.css","previous":786,"size":0,"diff":-786},{"filename":"route-home/index.tsx.chunk.d3be5.esm.js","previous":917,"size":0,"diff":-917},{"filename":"route-notfound/index.tsx.chunk.8dc19.css","previous":73,"size":0,"diff":-73},{"filename":"route-notfound/index.tsx.chunk.b11b8.esm.js","previous":340,"size":0,"diff":-340},{"filename":"bundle.bcfa9.js","previous":8143,"size":0,"diff":-8143},{"filename":"polyfills.84c13.js","previous":2012,"size":0,"diff":-2012},{"filename":"route-Privacy/index.tsx.chunk.56bc9.js","previous":439,"size":0,"diff":-439},{"filename":"route-home/index.tsx.chunk.7876f.js","previous":923,"size":0,"diff":-923},{"filename":"route-notfound/index.tsx.chunk.dc1d3.js","previous":340,"size":0,"diff":-340},{"filename":"ssr-bundle.42b42.css","previous":0,"size":1389,"diff":1389},{"filename":"ssr-bundle.js","previous":0,"size":4170,"diff":4170}]},{"timestamp":1592311829958,"files":[{"filename":"ssr-bundle.42b42.css","previous":1389,"size":0,"diff":-1389},{"filename":"ssr-bundle.js","previous":4170,"size":0,"diff":-4170},{"filename":"sw-esm.js","previous":0,"size":741,"diff":741},{"filename":"sw.js","previous":0,"size":738,"diff":738},{"filename":"bundle.76aa4.css","previous":0,"size":546,"diff":546},{"filename":"bundle.72487.esm.js","previous":0,"size":8158,"diff":8158},{"filename":"polyfills.989dd.esm.js","previous":0,"size":2012,"diff":2012},{"filename":"route-Privacy/index.tsx.chunk.19aa0.css","previous":0,"size":278,"diff":278},{"filename":"route-Privacy/index.tsx.chunk.85f50.esm.js","previous":0,"size":433,"diff":433},{"filename":"route-home/index.tsx.chunk.f4379.css","previous":0,"size":786,"diff":786},{"filename":"route-home/index.tsx.chunk.d3be5.esm.js","previous":0,"size":917,"diff":917},{"filename":"route-notfound/index.tsx.chunk.8dc19.css","previous":0,"size":73,"diff":73},{"filename":"route-notfound/index.tsx.chunk.b11b8.esm.js","previous":0,"size":340,"diff":340},{"filename":"bundle.bcfa9.js","previous":0,"size":8143,"diff":8143},{"filename":"polyfills.84c13.js","previous":0,"size":2012,"diff":2012},{"filename":"route-Privacy/index.tsx.chunk.56bc9.js","previous":0,"size":439,"diff":439},{"filename":"route-home/index.tsx.chunk.7876f.js","previous":0,"size":923,"diff":923},{"filename":"route-notfound/index.tsx.chunk.dc1d3.js","previous":0,"size":340,"diff":340}]},{"timestamp":1592311823559,"files":[{"filename":"sw-esm.js","previous":741,"size":0,"diff":-741},{"filename":"sw.js","previous":738,"size":0,"diff":-738},{"filename":"bundle.76aa4.css","previous":546,"size":0,"diff":-546},{"filename":"bundle.cb8c2.esm.js","previous":8156,"size":0,"diff":-8156},{"filename":"polyfills.989dd.esm.js","previous":2012,"size":0,"diff":-2012},{"filename":"route-Privacy/index.tsx.chunk.1995a.css","previous":281,"size":0,"diff":-281},{"filename":"route-Privacy/index.tsx.chunk.c9541.esm.js","previous":419,"size":0,"diff":-419},{"filename":"route-home/index.tsx.chunk.e69a3.css","previous":619,"size":0,"diff":-619},{"filename":"route-home/index.tsx.chunk.8da7d.esm.js","previous":562,"size":0,"diff":-562},{"filename":"route-notfound/index.tsx.chunk.8dc19.css","previous":73,"size":0,"diff":-73},{"filename":"route-notfound/index.tsx.chunk.b11b8.esm.js","previous":340,"size":0,"diff":-340},{"filename":"bundle.dea70.js","previous":8141,"size":0,"diff":-8141},{"filename":"polyfills.84c13.js","previous":2012,"size":0,"diff":-2012},{"filename":"route-Privacy/index.tsx.chunk.84ad3.js","previous":426,"size":0,"diff":-426},{"filename":"route-home/index.tsx.chunk.8b993.js","previous":566,"size":0,"diff":-566},{"filename":"route-notfound/index.tsx.chunk.dc1d3.js","previous":340,"size":0,"diff":-340},{"filename":"ssr-bundle.42b42.css","previous":0,"size":1389,"diff":1389},{"filename":"ssr-bundle.js","previous":0,"size":4170,"diff":4170}]},{"timestamp":1592130913623,"files":[{"filename":"ssr-bundle.e1f61.css","previous":1364,"size":0,"diff":-1364},{"filename":"ssr-bundle.js","previous":3913,"size":0,"diff":-3913},{"filename":"sw-esm.js","previous":0,"size":741,"diff":741},{"filename":"sw.js","previous":0,"size":738,"diff":738},{"filename":"bundle.76aa4.css","previous":0,"size":546,"diff":546},{"filename":"bundle.cb8c2.esm.js","previous":0,"size":8156,"diff":8156},{"filename":"polyfills.989dd.esm.js","previous":0,"size":2012,"diff":2012},{"filename":"route-Privacy/index.tsx.chunk.1995a.css","previous":0,"size":281,"diff":281},{"filename":"route-Privacy/index.tsx.chunk.c9541.esm.js","previous":0,"size":419,"diff":419},{"filename":"route-home/index.tsx.chunk.e69a3.css","previous":0,"size":619,"diff":619},{"filename":"route-home/index.tsx.chunk.8da7d.esm.js","previous":0,"size":562,"diff":562},{"filename":"route-notfound/index.tsx.chunk.8dc19.css","previous":0,"size":73,"diff":73},{"filename":"route-notfound/index.tsx.chunk.b11b8.esm.js","previous":0,"size":340,"diff":340},{"filename":"bundle.dea70.js","previous":0,"size":8141,"diff":8141},{"filename":"polyfills.84c13.js","previous":0,"size":2012,"diff":2012},{"filename":"route-Privacy/index.tsx.chunk.84ad3.js","previous":0,"size":426,"diff":426},{"filename":"route-home/index.tsx.chunk.8b993.js","previous":0,"size":566,"diff":566},{"filename":"route-notfound/index.tsx.chunk.dc1d3.js","previous":0,"size":340,"diff":340}]},{"timestamp":1592130907442,"files":[{"filename":"sw-esm.js","previous":741,"size":0,"diff":-741},{"filename":"sw.js","previous":738,"size":0,"diff":-738},{"filename":"bundle.76aa4.css","previous":546,"size":0,"diff":-546},{"filename":"bundle.e1e6e.esm.js","previous":8157,"size":0,"diff":-8157},{"filename":"polyfills.989dd.esm.js","previous":2012,"size":0,"diff":-2012},{"filename":"route-Privacy/index.tsx.chunk.827d5.css","previous":281,"size":0,"diff":-281},{"filename":"route-Privacy/index.tsx.chunk.4ee58.esm.js","previous":418,"size":0,"diff":-418},{"filename":"route-home/index.tsx.chunk.e69a3.css","previous":619,"size":0,"diff":-619},{"filename":"route-home/index.tsx.chunk.8da7d.esm.js","previous":562,"size":0,"diff":-562},{"filename":"route-notfound/index.tsx.chunk.8dc19.css","previous":73,"size":0,"diff":-73},{"filename":"route-notfound/index.tsx.chunk.b11b8.esm.js","previous":340,"size":0,"diff":-340},{"filename":"bundle.622cf.js","previous":8144,"size":0,"diff":-8144},{"filename":"polyfills.84c13.js","previous":2012,"size":0,"diff":-2012},{"filename":"route-Privacy/index.tsx.chunk.12829.js","previous":426,"size":0,"diff":-426},{"filename":"route-home/index.tsx.chunk.8b993.js","previous":566,"size":0,"diff":-566},{"filename":"route-notfound/index.tsx.chunk.dc1d3.js","previous":340,"size":0,"diff":-340},{"filename":"ssr-bundle.e1f61.css","previous":0,"size":1364,"diff":1364},{"filename":"ssr-bundle.js","previous":0,"size":3913,"diff":3913}]},{"timestamp":1592130864583,"files":[{"filename":"ssr-bundle.6209d.css","previous":1365,"size":0,"diff":-1365},{"filename":"ssr-bundle.js","previous":3913,"size":0,"diff":-3913},{"filename":"sw-esm.js","previous":0,"size":741,"diff":741},{"filename":"sw.js","previous":0,"size":738,"diff":738},{"filename":"bundle.76aa4.css","previous":0,"size":546,"diff":546},{"filename":"bundle.e1e6e.esm.js","previous":0,"size":8157,"diff":8157},{"filename":"polyfills.989dd.esm.js","previous":0,"size":2012,"diff":2012},{"filename":"route-Privacy/index.tsx.chunk.827d5.css","previous":0,"size":281,"diff":281},{"filename":"route-Privacy/index.tsx.chunk.4ee58.esm.js","previous":0,"size":418,"diff":418},{"filename":"route-home/index.tsx.chunk.e69a3.css","previous":0,"size":619,"diff":619},{"filename":"route-home/index.tsx.chunk.8da7d.esm.js","previous":0,"size":562,"diff":562},{"filename":"route-notfound/index.tsx.chunk.8dc19.css","previous":0,"size":73,"diff":73},{"filename":"route-notfound/index.tsx.chunk.b11b8.esm.js","previous":0,"size":340,"diff":340},{"filename":"bundle.622cf.js","previous":0,"size":8144,"diff":8144},{"filename":"polyfills.84c13.js","previous":0,"size":2012,"diff":2012},{"filename":"route-Privacy/index.tsx.chunk.12829.js","previous":0,"size":426,"diff":426},{"filename":"route-home/index.tsx.chunk.8b993.js","previous":0,"size":566,"diff":566},{"filename":"route-notfound/index.tsx.chunk.dc1d3.js","previous":0,"size":340,"diff":340}]},{"timestamp":1592130858676,"files":[{"filename":"sw-esm.js","previous":741,"size":0,"diff":-741},{"filename":"sw.js","previous":738,"size":0,"diff":-738},{"filename":"bundle.76aa4.css","previous":546,"size":0,"diff":-546},{"filename":"bundle.447ed.esm.js","previous":8164,"size":0,"diff":-8164},{"filename":"polyfills.989dd.esm.js","previous":2012,"size":0,"diff":-2012},{"filename":"route-Privacy/index.tsx.chunk.827d5.css","previous":281,"size":0,"diff":-281},{"filename":"route-Privacy/index.tsx.chunk.4ee58.esm.js","previous":418,"size":0,"diff":-418},{"filename":"route-home/index.tsx.chunk.e69a3.css","previous":619,"size":0,"diff":-619},{"filename":"route-home/index.tsx.chunk.8da7d.esm.js","previous":562,"size":0,"diff":-562},{"filename":"route-notfound/index.tsx.chunk.8dc19.css","previous":73,"size":0,"diff":-73},{"filename":"route-notfound/index.tsx.chunk.b11b8.esm.js","previous":340,"size":0,"diff":-340},{"filename":"bundle.52d80.js","previous":8151,"size":0,"diff":-8151},{"filename":"polyfills.84c13.js","previous":2012,"size":0,"diff":-2012},{"filename":"route-Privacy/index.tsx.chunk.12829.js","previous":426,"size":0,"diff":-426},{"filename":"route-home/index.tsx.chunk.8b993.js","previous":566,"size":0,"diff":-566},{"filename":"route-notfound/index.tsx.chunk.dc1d3.js","previous":340,"size":0,"diff":-340},{"filename":"ssr-bundle.6209d.css","previous":0,"size":1365,"diff":1365},{"filename":"ssr-bundle.js","previous":0,"size":3913,"diff":3913}]},{"timestamp":1592130826227,"files":[{"filename":"ssr-bundle.6209d.css","previous":1365,"size":0,"diff":-1365},{"filename":"ssr-bundle.js","previous":3918,"size":0,"diff":-3918},{"filename":"sw-esm.js","previous":0,"size":741,"diff":741},{"filename":"sw.js","previous":0,"size":738,"diff":738},{"filename":"bundle.76aa4.css","previous":0,"size":546,"diff":546},{"filename":"bundle.447ed.esm.js","previous":0,"size":8164,"diff":8164},{"filename":"polyfills.989dd.esm.js","previous":0,"size":2012,"diff":2012},{"filename":"route-Privacy/index.tsx.chunk.827d5.css","previous":0,"size":281,"diff":281},{"filename":"route-Privacy/index.tsx.chunk.4ee58.esm.js","previous":0,"size":418,"diff":418},{"filename":"route-home/index.tsx.chunk.e69a3.css","previous":0,"size":619,"diff":619},{"filename":"route-home/index.tsx.chunk.8da7d.esm.js","previous":0,"size":562,"diff":562},{"filename":"route-notfound/index.tsx.chunk.8dc19.css","previous":0,"size":73,"diff":73},{"filename":"route-notfound/index.tsx.chunk.b11b8.esm.js","previous":0,"size":340,"diff":340},{"filename":"bundle.52d80.js","previous":0,"size":8151,"diff":8151},{"filename":"polyfills.84c13.js","previous":0,"size":2012,"diff":2012},{"filename":"route-Privacy/index.tsx.chunk.12829.js","previous":0,"size":426,"diff":426},{"filename":"route-home/index.tsx.chunk.8b993.js","previous":0,"size":566,"diff":566},{"filename":"route-notfound/index.tsx.chunk.dc1d3.js","previous":0,"size":340,"diff":340}]},{"timestamp":1592130820326,"files":[{"filename":"sw-esm.js","previous":741,"size":0,"diff":-741},{"filename":"sw.js","previous":738,"size":0,"diff":-738},{"filename":"bundle.76aa4.css","previous":546,"size":0,"diff":-546},{"filename":"bundle.e7499.esm.js","previous":8176,"size":0,"diff":-8176},{"filename":"polyfills.989dd.esm.js","previous":2012,"size":0,"diff":-2012},{"filename":"route-Privacy/index.tsx.chunk.827d5.css","previous":281,"size":0,"diff":-281},{"filename":"route-Privacy/index.tsx.chunk.4ee58.esm.js","previous":418,"size":0,"diff":-418},{"filename":"route-home/index.tsx.chunk.e69a3.css","previous":619,"size":0,"diff":-619},{"filename":"route-home/index.tsx.chunk.8da7d.esm.js","previous":562,"size":0,"diff":-562},{"filename":"route-notfound/index.tsx.chunk.8dc19.css","previous":73,"size":0,"diff":-73},{"filename":"route-notfound/index.tsx.chunk.b11b8.esm.js","previous":340,"size":0,"diff":-340},{"filename":"bundle.cd3f5.js","previous":8159,"size":0,"diff":-8159},{"filename":"polyfills.84c13.js","previous":2012,"size":0,"diff":-2012},{"filename":"route-Privacy/index.tsx.chunk.12829.js","previous":426,"size":0,"diff":-426},{"filename":"route-home/index.tsx.chunk.8b993.js","previous":566,"size":0,"diff":-566},{"filename":"route-notfound/index.tsx.chunk.dc1d3.js","previous":340,"size":0,"diff":-340},{"filename":"ssr-bundle.6209d.css","previous":0,"size":1365,"diff":1365},{"filename":"ssr-bundle.js","previous":0,"size":3918,"diff":3918}]},{"timestamp":1592130779270,"files":[{"filename":"ssr-bundle.6209d.css","previous":1365,"size":0,"diff":-1365},{"filename":"ssr-bundle.js","previous":3930,"size":0,"diff":-3930},{"filename":"sw-esm.js","previous":0,"size":741,"diff":741},{"filename":"sw.js","previous":0,"size":738,"diff":738},{"filename":"bundle.76aa4.css","previous":0,"size":546,"diff":546},{"filename":"bundle.e7499.esm.js","previous":0,"size":8176,"diff":8176},{"filename":"polyfills.989dd.esm.js","previous":0,"size":2012,"diff":2012},{"filename":"route-Privacy/index.tsx.chunk.827d5.css","previous":0,"size":281,"diff":281},{"filename":"route-Privacy/index.tsx.chunk.4ee58.esm.js","previous":0,"size":418,"diff":418},{"filename":"route-home/index.tsx.chunk.e69a3.css","previous":0,"size":619,"diff":619},{"filename":"route-home/index.tsx.chunk.8da7d.esm.js","previous":0,"size":562,"diff":562},{"filename":"route-notfound/index.tsx.chunk.8dc19.css","previous":0,"size":73,"diff":73},{"filename":"route-notfound/index.tsx.chunk.b11b8.esm.js","previous":0,"size":340,"diff":340},{"filename":"bundle.cd3f5.js","previous":0,"size":8159,"diff":8159},{"filename":"polyfills.84c13.js","previous":0,"size":2012,"diff":2012},{"filename":"route-Privacy/index.tsx.chunk.12829.js","previous":0,"size":426,"diff":426},{"filename":"route-home/index.tsx.chunk.8b993.js","previous":0,"size":566,"diff":566},{"filename":"route-notfound/index.tsx.chunk.dc1d3.js","previous":0,"size":340,"diff":340}]},{"timestamp":1592130773374,"files":[{"filename":"sw-esm.js","previous":741,"size":0,"diff":-741},{"filename":"sw.js","previous":738,"size":0,"diff":-738},{"filename":"bundle.76aa4.css","previous":546,"size":0,"diff":-546},{"filename":"bundle.e6b27.esm.js","previous":8162,"size":0,"diff":-8162},{"filename":"polyfills.989dd.esm.js","previous":2012,"size":0,"diff":-2012},{"filename":"route-Privacy/index.tsx.chunk.827d5.css","previous":281,"size":0,"diff":-281},{"filename":"route-Privacy/index.tsx.chunk.4ee58.esm.js","previous":418,"size":0,"diff":-418},{"filename":"route-home/index.tsx.chunk.e69a3.css","previous":619,"size":0,"diff":-619},{"filename":"route-home/index.tsx.chunk.8da7d.esm.js","previous":562,"size":0,"diff":-562},{"filename":"route-notfound/index.tsx.chunk.8dc19.css","previous":73,"size":0,"diff":-73},{"filename":"route-notfound/index.tsx.chunk.b11b8.esm.js","previous":340,"size":0,"diff":-340},{"filename":"bundle.c3b28.js","previous":8148,"size":0,"diff":-8148},{"filename":"polyfills.84c13.js","previous":2012,"size":0,"diff":-2012},{"filename":"route-Privacy/index.tsx.chunk.12829.js","previous":426,"size":0,"diff":-426},{"filename":"route-home/index.tsx.chunk.8b993.js","previous":566,"size":0,"diff":-566},{"filename":"route-notfound/index.tsx.chunk.dc1d3.js","previous":340,"size":0,"diff":-340},{"filename":"ssr-bundle.6209d.css","previous":0,"size":1365,"diff":1365},{"filename":"ssr-bundle.js","previous":0,"size":3930,"diff":3930}]},{"timestamp":1592130502712,"files":[{"filename":"ssr-bundle.6209d.css","previous":1365,"size":0,"diff":-1365},{"filename":"ssr-bundle.js","previous":3916,"size":0,"diff":-3916},{"filename":"sw-esm.js","previous":0,"size":741,"diff":741},{"filename":"sw.js","previous":0,"size":738,"diff":738},{"filename":"bundle.76aa4.css","previous":0,"size":546,"diff":546},{"filename":"bundle.e6b27.esm.js","previous":0,"size":8162,"diff":8162},{"filename":"polyfills.989dd.esm.js","previous":0,"size":2012,"diff":2012},{"filename":"route-Privacy/index.tsx.chunk.827d5.css","previous":0,"size":281,"diff":281},{"filename":"route-Privacy/index.tsx.chunk.4ee58.esm.js","previous":0,"size":418,"diff":418},{"filename":"route-home/index.tsx.chunk.e69a3.css","previous":0,"size":619,"diff":619},{"filename":"route-home/index.tsx.chunk.8da7d.esm.js","previous":0,"size":562,"diff":562},{"filename":"route-notfound/index.tsx.chunk.8dc19.css","previous":0,"size":73,"diff":73},{"filename":"route-notfound/index.tsx.chunk.b11b8.esm.js","previous":0,"size":340,"diff":340},{"filename":"bundle.c3b28.js","previous":0,"size":8148,"diff":8148},{"filename":"polyfills.84c13.js","previous":0,"size":2012,"diff":2012},{"filename":"route-Privacy/index.tsx.chunk.12829.js","previous":0,"size":426,"diff":426},{"filename":"route-home/index.tsx.chunk.8b993.js","previous":0,"size":566,"diff":566},{"filename":"route-notfound/index.tsx.chunk.dc1d3.js","previous":0,"size":340,"diff":340}]},{"timestamp":1592130496604,"files":[{"filename":"sw-esm.js","previous":741,"size":0,"diff":-741},{"filename":"sw.js","previous":738,"size":0,"diff":-738},{"filename":"bundle.76aa4.css","previous":546,"size":0,"diff":-546},{"filename":"bundle.e6b27.esm.js","previous":8162,"size":0,"diff":-8162},{"filename":"polyfills.989dd.esm.js","previous":2012,"size":0,"diff":-2012},{"filename":"route-Privacy/index.tsx.chunk.827d5.css","previous":281,"size":0,"diff":-281},{"filename":"route-Privacy/index.tsx.chunk.4ee58.esm.js","previous":418,"size":0,"diff":-418},{"filename":"route-home/index.tsx.chunk.e69a3.css","previous":619,"size":0,"diff":-619},{"filename":"route-home/index.tsx.chunk.8da7d.esm.js","previous":562,"size":0,"diff":-562},{"filename":"route-notfound/index.tsx.chunk.8dc19.css","previous":73,"size":0,"diff":-73},{"filename":"route-notfound/index.tsx.chunk.b11b8.esm.js","previous":340,"size":0,"diff":-340},{"filename":"bundle.c3b28.js","previous":8148,"size":0,"diff":-8148},{"filename":"polyfills.84c13.js","previous":2012,"size":0,"diff":-2012},{"filename":"route-Privacy/index.tsx.chunk.12829.js","previous":426,"size":0,"diff":-426},{"filename":"route-home/index.tsx.chunk.8b993.js","previous":566,"size":0,"diff":-566},{"filename":"route-notfound/index.tsx.chunk.dc1d3.js","previous":340,"size":0,"diff":-340},{"filename":"ssr-bundle.6209d.css","previous":0,"size":1365,"diff":1365},{"filename":"ssr-bundle.js","previous":0,"size":3916,"diff":3916}]},{"timestamp":1592130433628,"files":[{"filename":"ssr-bundle.6209d.css","previous":1365,"size":0,"diff":-1365},{"filename":"ssr-bundle.js","previous":3916,"size":0,"diff":-3916},{"filename":"sw-esm.js","previous":0,"size":741,"diff":741},{"filename":"sw.js","previous":0,"size":738,"diff":738},{"filename":"bundle.76aa4.css","previous":0,"size":546,"diff":546},{"filename":"bundle.e6b27.esm.js","previous":0,"size":8162,"diff":8162},{"filename":"polyfills.989dd.esm.js","previous":0,"size":2012,"diff":2012},{"filename":"route-Privacy/index.tsx.chunk.827d5.css","previous":0,"size":281,"diff":281},{"filename":"route-Privacy/index.tsx.chunk.4ee58.esm.js","previous":0,"size":418,"diff":418},{"filename":"route-home/index.tsx.chunk.e69a3.css","previous":0,"size":619,"diff":619},{"filename":"route-home/index.tsx.chunk.8da7d.esm.js","previous":0,"size":562,"diff":562},{"filename":"route-notfound/index.tsx.chunk.8dc19.css","previous":0,"size":73,"diff":73},{"filename":"route-notfound/index.tsx.chunk.b11b8.esm.js","previous":0,"size":340,"diff":340},{"filename":"bundle.c3b28.js","previous":0,"size":8148,"diff":8148},{"filename":"polyfills.84c13.js","previous":0,"size":2012,"diff":2012},{"filename":"route-Privacy/index.tsx.chunk.12829.js","previous":0,"size":426,"diff":426},{"filename":"route-home/index.tsx.chunk.8b993.js","previous":0,"size":566,"diff":566},{"filename":"route-notfound/index.tsx.chunk.dc1d3.js","previous":0,"size":340,"diff":340}]},{"timestamp":1592130427299,"files":[{"filename":"sw-esm.js","previous":741,"size":0,"diff":-741},{"filename":"sw.js","previous":738,"size":0,"diff":-738},{"filename":"bundle.cf5ad.css","previous":547,"size":0,"diff":-547},{"filename":"bundle.2fb1a.esm.js","previous":8165,"size":0,"diff":-8165},{"filename":"polyfills.989dd.esm.js","previous":2012,"size":0,"diff":-2012},{"filename":"route-Privacy/index.tsx.chunk.5b6c4.css","previous":280,"size":0,"diff":-280},{"filename":"route-Privacy/index.tsx.chunk.23b83.esm.js","previous":417,"size":0,"diff":-417},{"filename":"route-home/index.tsx.chunk.a3d9b.css","previous":625,"size":0,"diff":-625},{"filename":"route-home/index.tsx.chunk.32f64.esm.js","previous":477,"size":0,"diff":-477},{"filename":"route-notfound/index.tsx.chunk.76830.css","previous":73,"size":0,"diff":-73},{"filename":"route-notfound/index.tsx.chunk.34cde.esm.js","previous":339,"size":0,"diff":-339},{"filename":"bundle.71fdc.js","previous":8148,"size":0,"diff":-8148},{"filename":"polyfills.84c13.js","previous":2012,"size":0,"diff":-2012},{"filename":"route-Privacy/index.tsx.chunk.dff3f.js","previous":424,"size":0,"diff":-424},{"filename":"route-home/index.tsx.chunk.0f6c8.js","previous":481,"size":0,"diff":-481},{"filename":"route-notfound/index.tsx.chunk.b681a.js","previous":341,"size":0,"diff":-341},{"filename":"ssr-bundle.6209d.css","previous":0,"size":1365,"diff":1365},{"filename":"ssr-bundle.js","previous":0,"size":3916,"diff":3916}]},{"timestamp":1589819946801,"files":[{"filename":"ssr-bundle.19a7b.css","previous":1384,"size":0,"diff":-1384},{"filename":"ssr-bundle.js","previous":3833,"size":0,"diff":-3833},{"filename":"sw-esm.js","previous":0,"size":741,"diff":741},{"filename":"sw.js","previous":0,"size":738,"diff":738},{"filename":"bundle.cf5ad.css","previous":0,"size":547,"diff":547},{"filename":"bundle.2fb1a.esm.js","previous":0,"size":8165,"diff":8165},{"filename":"polyfills.989dd.esm.js","previous":0,"size":2012,"diff":2012},{"filename":"route-Privacy/index.tsx.chunk.5b6c4.css","previous":0,"size":280,"diff":280},{"filename":"route-Privacy/index.tsx.chunk.23b83.esm.js","previous":0,"size":417,"diff":417},{"filename":"route-home/index.tsx.chunk.a3d9b.css","previous":0,"size":625,"diff":625},{"filename":"route-home/index.tsx.chunk.32f64.esm.js","previous":0,"size":477,"diff":477},{"filename":"route-notfound/index.tsx.chunk.76830.css","previous":0,"size":73,"diff":73},{"filename":"route-notfound/index.tsx.chunk.34cde.esm.js","previous":0,"size":339,"diff":339},{"filename":"bundle.71fdc.js","previous":0,"size":8148,"diff":8148},{"filename":"polyfills.84c13.js","previous":0,"size":2012,"diff":2012},{"filename":"route-Privacy/index.tsx.chunk.dff3f.js","previous":0,"size":424,"diff":424},{"filename":"route-home/index.tsx.chunk.0f6c8.js","previous":0,"size":481,"diff":481},{"filename":"route-notfound/index.tsx.chunk.b681a.js","previous":0,"size":341,"diff":341}]},{"timestamp":1589819937153,"files":[{"filename":"sw-esm.js","previous":741,"size":0,"diff":-741},{"filename":"sw.js","previous":738,"size":0,"diff":-738},{"filename":"bundle.cf5ad.css","previous":547,"size":0,"diff":-547},{"filename":"bundle.2fb1a.esm.js","previous":8165,"size":0,"diff":-8165},{"filename":"polyfills.989dd.esm.js","previous":2012,"size":0,"diff":-2012},{"filename":"route-Privacy/index.tsx.chunk.5b6c4.css","previous":280,"size":0,"diff":-280},{"filename":"route-Privacy/index.tsx.chunk.23b83.esm.js","previous":417,"size":0,"diff":-417},{"filename":"route-home/index.tsx.chunk.a3d9b.css","previous":625,"size":0,"diff":-625},{"filename":"route-home/index.tsx.chunk.32f64.esm.js","previous":477,"size":0,"diff":-477},{"filename":"route-notfound/index.tsx.chunk.76830.css","previous":73,"size":0,"diff":-73},{"filename":"route-notfound/index.tsx.chunk.34cde.esm.js","previous":339,"size":0,"diff":-339},{"filename":"bundle.71fdc.js","previous":8148,"size":0,"diff":-8148},{"filename":"polyfills.84c13.js","previous":2012,"size":0,"diff":-2012},{"filename":"route-Privacy/index.tsx.chunk.dff3f.js","previous":424,"size":0,"diff":-424},{"filename":"route-home/index.tsx.chunk.0f6c8.js","previous":481,"size":0,"diff":-481},{"filename":"route-notfound/index.tsx.chunk.b681a.js","previous":341,"size":0,"diff":-341},{"filename":"ssr-bundle.19a7b.css","previous":0,"size":1384,"diff":1384},{"filename":"ssr-bundle.js","previous":0,"size":3833,"diff":3833}]},{"timestamp":1589819702588,"files":[{"filename":"ssr-bundle.19a7b.css","previous":1384,"size":0,"diff":-1384},{"filename":"ssr-bundle.js","previous":3833,"size":0,"diff":-3833},{"filename":"sw-esm.js","previous":0,"size":741,"diff":741},{"filename":"sw.js","previous":0,"size":738,"diff":738},{"filename":"bundle.cf5ad.css","previous":0,"size":547,"diff":547},{"filename":"bundle.2fb1a.esm.js","previous":0,"size":8165,"diff":8165},{"filename":"polyfills.989dd.esm.js","previous":0,"size":2012,"diff":2012},{"filename":"route-Privacy/index.tsx.chunk.5b6c4.css","previous":0,"size":280,"diff":280},{"filename":"route-Privacy/index.tsx.chunk.23b83.esm.js","previous":0,"size":417,"diff":417},{"filename":"route-home/index.tsx.chunk.a3d9b.css","previous":0,"size":625,"diff":625},{"filename":"route-home/index.tsx.chunk.32f64.esm.js","previous":0,"size":477,"diff":477},{"filename":"route-notfound/index.tsx.chunk.76830.css","previous":0,"size":73,"diff":73},{"filename":"route-notfound/index.tsx.chunk.34cde.esm.js","previous":0,"size":339,"diff":339},{"filename":"bundle.71fdc.js","previous":0,"size":8148,"diff":8148},{"filename":"polyfills.84c13.js","previous":0,"size":2012,"diff":2012},{"filename":"route-Privacy/index.tsx.chunk.dff3f.js","previous":0,"size":424,"diff":424},{"filename":"route-home/index.tsx.chunk.0f6c8.js","previous":0,"size":481,"diff":481},{"filename":"route-notfound/index.tsx.chunk.b681a.js","previous":0,"size":341,"diff":341}]},{"timestamp":1589819535769,"files":[{"filename":"ssr-bundle.19a7b.css","previous":0,"size":1384,"diff":1384},{"filename":"ssr-bundle.js","previous":0,"size":3833,"diff":3833}]}]
